Metadata-Version: 2.1
Name: st-format
Version: 0.2
Summary: Utility functions for enhancing Streamlit apps
Home-page: https://github.com/Willy71/st_format
Author: Guillermo Cerato
Author-email: gcerato@gmail.com
License: MIT License
Keywords: utilitys streamlit center text background
License-File: LICENSE
